ghPublish/auth.py
ghPublish/__init__.py
ghPublish/base_html.py
ghPublish/cli.py
ghPublish/ghPublish.py
ghPublish/preview.py
ghPublish-1.0.1.dist-info/METADATA
ghPublish-1.0.1.dist-info/entry_points.txt
ghPublish-1.0.1.dist-info/top_level.txt
ghPublish-1.0.1.dist-info/RECORD
ghPublish-1.0.1.dist-info/WHEEL
ghPublish-1.0.1.dist-info/metadata.json
ghPublish-1.0.1.dist-info/DESCRIPTION.rst
