Metadata-Version: 2.0
Name: ghPublish
Version: 1.0.1
Summary: Directly publish your blog posts to GitHub Pages from the command line.
Home-page: https://github.com/MiteshNinja/ghPublish
Author: Mitesh Shah
Author-email: mitesh@miteshshah.com
License: UNKNOWN
Download-URL: https://github.com/MiteshNinja/ghPublish/tarball/1.0.1
Keywords: github,publish,blog,pages,cli
Platform: UNKNOWN
Requires-Dist: pygments
Requires-Dist: mistune
Requires-Dist: requests
